rapyuta_io_sdk_v2/__init__.py
rapyuta_io_sdk_v2/async_client.py
rapyuta_io_sdk_v2/client.py
rapyuta_io_sdk_v2/config.py
rapyuta_io_sdk_v2/constants.py
rapyuta_io_sdk_v2/exceptions.py
rapyuta_io_sdk_v2/py.typed
rapyuta_io_sdk_v2/utils.py
rapyuta_io_sdk_v2/pydantic_source/__init__.py
rapyuta_io_sdk_v2/pydantic_source/source.py
rapyuta_io_sdk_v2-0.2.4.dist-info/METADATA
rapyuta_io_sdk_v2-0.2.4.dist-info/WHEEL
rapyuta_io_sdk_v2-0.2.4.dist-info/licenses/LICENSE
rapyuta_io_sdk_v2-0.2.4.dist-info/RECORD
