Metadata-Version: 2.4
Name: rapyuta-io-sdk-v2
Version: 0.2.4
Summary: Python SDK for rapyuta.io v2 APIs
License:                                  Apache License
License-File: LICENSE
Requires-Python: >=3.8
Requires-Dist: httpx>=0.27.2
Requires-Dist: munch>=4.0.0
Requires-Dist: pydantic-settings>=2.7.1
Requires-Dist: python-benedict>=0.34.1
Requires-Dist: pyyaml>=6.0.2
